<amc>
  <content>
    <des>
      <sample_temp>
        <value>20.244567</value>
        <unit>C</unit>
      </sample_temp>
      <index>0</index>
      <volume>
        <value>0.101299378</value>
        <unit>L</unit>
      </volume>
      <pressure>
        <value>45.790414429</value>
        <unit>bar</unit>
      </pressure>
      <time>
        <value>1.001</value>
        <unit>s (seconds)</unit>
      </time>
      <serial>
        <value>0.0</value>
        <unit/>
      </serial>
      <concentration>
        <value>2.86350340909</value>
        <unit>mmol/g</unit>
      </concentration>
    </des>
    <des>
      <sample_temp>
        <value>19.891465</value>
        <unit>C</unit>
      </sample_temp>
      <index>1</index>
      <volume>
        <value>0.100048679</value>
        <unit>L</unit>
      </volume>
      <pressure>
        <value>43.8220893708</value>
        <unit>bar</unit>
      </pressure>
      <time>
        <value>1985.997</value>
        <unit>s (seconds)</unit>
      </time>
      <serial>
        <value>1.0</value>
        <unit/>
      </serial>
      <concentration>
        <value>2.82814909091</value>
        <unit>mmol/g</unit>
      </concentration>
    </des>
    <des>
      <sample_temp>
        <value>19.949139</value>
        <unit>C</unit>
      </sample_temp>
      <index>2</index>
      <volume>
        <value>0.100537446</value>
        <unit>L</unit>
      </volume>
      <pressure>
        <value>41.7318775965</value>
        <unit>bar</unit>
      </pressure>
      <time>
        <value>3986.995</value>
        <unit>s (seconds)</unit>
      </time>
      <serial>
        <value>2.0</value>
        <unit/>
      </serial>
      <concentration>
        <value>2.84196522727</value>
        <unit>mmol/g</unit>
      </concentration>
    </des>
    <des>
      <sample_temp>
        <value>19.850673</value>
        <unit>C</unit>
      </sample_temp>
      <index>3</index>
      <volume>
        <value>0.101204456</value>
        <unit>L</unit>
      </volume>
      <pressure>
        <value>39.6778700983</value>
        <unit>bar</unit>
      </pressure>
      <time>
        <value>5973.996</value>
        <unit>s (seconds)</unit>
      </time>
      <serial>
        <value>3.0</value>
        <unit/>
      </serial>
      <concentration>
        <value>2.86082022727</value>
        <unit>mmol/g</unit>
      </concentration>
    </des>
    <des>
      <sample_temp>
        <value>19.803013</value>
        <unit>C</unit>
      </sample_temp>
      <index>4</index>
      <volume>
        <value>0.102086996</value>
        <unit>L</unit>
      </volume>
      <pressure>
        <value>37.7051069004</value>
        <unit>bar</unit>
      </pressure>
      <time>
        <value>7999.995</value>
        <unit>s (seconds)</unit>
      </time>
      <serial>
        <value>4.0</value>
        <unit/>
      </serial>
      <concentration>
        <value>2.8857675</value>
        <unit>mmol/g</unit>
      </concentration>
    </des>
    <des>
      <sample_temp>
        <value>20.038215</value>
        <unit>C</unit>
      </sample_temp>
      <index>5</index>
      <volume>
        <value>0.103629341</value>
        <unit>L</unit>
      </volume>
      <pressure>
        <value>35.6427297599</value>
        <unit>bar</unit>
      </pressure>
      <time>
        <value>9986.992</value>
        <unit>s (seconds)</unit>
      </time>
      <serial>
        <value>5.0</value>
        <unit/>
      </serial>
      <concentration>
        <value>2.92936613636</value>
        <unit>mmol/g</unit>
      </concentration>
    </des>
    <des>
      <sample_temp>
        <value>20.069047</value>
        <unit>C</unit>
      </sample_temp>
      <index>6</index>
      <volume>
        <value>0.104523642</value>
        <unit>L</unit>
      </volume>
      <pressure>
        <value>33.7341169318</value>
        <unit>bar</unit>
      </pressure>
      <time>
        <value>11939.992</value>
        <unit>s (seconds)</unit>
      </time>
      <serial>
        <value>6.0</value>
        <unit/>
      </serial>
      <concentration>
        <value>2.95464590909</value>
        <unit>mmol/g</unit>
      </concentration>
    </des>
    <des>
      <sample_temp>
        <value>19.884093</value>
        <unit>C</unit>
      </sample_temp>
      <index>7</index>
      <volume>
        <value>0.105684299</value>
        <unit>L</unit>
      </volume>
      <pressure>
        <value>31.8405208228</value>
        <unit>bar</unit>
      </pressure>
      <time>
        <value>14007.002</value>
        <unit>s (seconds)</unit>
      </time>
      <serial>
        <value>7.0</value>
        <unit/>
      </serial>
      <concentration>
        <value>2.98745522727</value>
        <unit>mmol/g</unit>
      </concentration>
    </des>
    <des>
      <sample_temp>
        <value>20.315125</value>
        <unit>C</unit>
      </sample_temp>
      <index>8</index>
      <volume>
        <value>0.106863903</value>
        <unit>L</unit>
      </volume>
      <pressure>
        <value>29.7298105178</value>
        <unit>bar</unit>
      </pressure>
      <time>
        <value>15995.997</value>
        <unit>s (seconds)</unit>
      </time>
      <serial>
        <value>8.0</value>
        <unit/>
      </serial>
      <concentration>
        <value>3.0208</value>
        <unit>mmol/g</unit>
      </concentration>
    </des>
    <des>
      <sample_temp>
        <value>20.167972</value>
        <unit>C</unit>
      </sample_temp>
      <index>9</index>
      <volume>
        <value>0.108025581</value>
        <unit>L</unit>
      </volume>
      <pressure>
        <value>27.766318776</value>
        <unit>bar</unit>
      </pressure>
      <time>
        <value>18087.02</value>
        <unit>s (seconds)</unit>
      </time>
      <serial>
        <value>9.0</value>
        <unit/>
      </serial>
      <concentration>
        <value>3.05363795455</value>
        <unit>mmol/g</unit>
      </concentration>
    </des>
    <des>
      <sample_temp>
        <value>19.743158</value>
        <unit>C</unit>
      </sample_temp>
      <index>10</index>
      <volume>
        <value>0.108828458</value>
        <unit>L</unit>
      </volume>
      <pressure>
        <value>25.7175904347</value>
        <unit>bar</unit>
      </pressure>
      <time>
        <value>20132.014</value>
        <unit>s (seconds)</unit>
      </time>
      <serial>
        <value>10.0</value>
        <unit/>
      </serial>
      <concentration>
        <value>3.07633340909</value>
        <unit>mmol/g</unit>
      </concentration>
    </des>
    <des>
      <sample_temp>
        <value>20.194804</value>
        <unit>C</unit>
      </sample_temp>
      <index>11</index>
      <volume>
        <value>0.110142583</value>
        <unit>L</unit>
      </volume>
      <pressure>
        <value>23.585408856</value>
        <unit>bar</unit>
      </pressure>
      <time>
        <value>22099.01</value>
        <unit>s (seconds)</unit>
      </time>
      <serial>
        <value>11.0</value>
        <unit/>
      </serial>
      <concentration>
        <value>3.11348068182</value>
        <unit>mmol/g</unit>
      </concentration>
    </des>
    <des>
      <sample_temp>
        <value>19.773047</value>
        <unit>C</unit>
      </sample_temp>
      <index>12</index>
      <volume>
        <value>0.110866869</value>
        <unit>L</unit>
      </volume>
      <pressure>
        <value>21.47380687</value>
        <unit>bar</unit>
      </pressure>
      <time>
        <value>24080.004</value>
        <unit>s (seconds)</unit>
      </time>
      <serial>
        <value>12.0</value>
        <unit/>
      </serial>
      <concentration>
        <value>3.13395454545</value>
        <unit>mmol/g</unit>
      </concentration>
    </des>
    <des>
      <sample_temp>
        <value>20.031126</value>
        <unit>C</unit>
      </sample_temp>
      <index>13</index>
      <volume>
        <value>0.111845126</value>
        <unit>L</unit>
      </volume>
      <pressure>
        <value>19.3626912554</value>
        <unit>bar</unit>
      </pressure>
      <time>
        <value>26074.994</value>
        <unit>s (seconds)</unit>
      </time>
      <serial>
        <value>13.0</value>
        <unit/>
      </serial>
      <concentration>
        <value>3.16160772727</value>
        <unit>mmol/g</unit>
      </concentration>
    </des>
    <des>
      <sample_temp>
        <value>19.694663</value>
        <unit>C</unit>
      </sample_temp>
      <index>14</index>
      <volume>
        <value>0.112396438</value>
        <unit>L</unit>
      </volume>
      <pressure>
        <value>17.2814672206</value>
        <unit>bar</unit>
      </pressure>
      <time>
        <value>28100.998</value>
        <unit>s (seconds)</unit>
      </time>
      <serial>
        <value>14.0</value>
        <unit/>
      </serial>
      <concentration>
        <value>3.17719204545</value>
        <unit>mmol/g</unit>
      </concentration>
    </des>
    <des>
      <sample_temp>
        <value>19.97076</value>
        <unit>C</unit>
      </sample_temp>
      <index>15</index>
      <volume>
        <value>0.112956177</value>
        <unit>L</unit>
      </volume>
      <pressure>
        <value>15.1904954909</value>
        <unit>bar</unit>
      </pressure>
      <time>
        <value>30089.018</value>
        <unit>s (seconds)</unit>
      </time>
      <serial>
        <value>15.0</value>
        <unit/>
      </serial>
      <concentration>
        <value>3.19301454545</value>
        <unit>mmol/g</unit>
      </concentration>
    </des>
    <des>
      <sample_temp>
        <value>20.230323</value>
        <unit>C</unit>
      </sample_temp>
      <index>16</index>
      <volume>
        <value>0.113330788</value>
        <unit>L</unit>
      </volume>
      <pressure>
        <value>13.0947107103</value>
        <unit>bar</unit>
      </pressure>
      <time>
        <value>32114.996</value>
        <unit>s (seconds)</unit>
      </time>
      <serial>
        <value>16.0</value>
        <unit/>
      </serial>
      <concentration>
        <value>3.20360409091</value>
        <unit>mmol/g</unit>
      </concentration>
    </des>
    <des>
      <sample_temp>
        <value>20.243562</value>
        <unit>C</unit>
      </sample_temp>
      <index>17</index>
      <volume>
        <value>0.113108048</value>
        <unit>L</unit>
      </volume>
      <pressure>
        <value>10.9762792583</value>
        <unit>bar</unit>
      </pressure>
      <time>
        <value>34116.994</value>
        <unit>s (seconds)</unit>
      </time>
      <serial>
        <value>17.0</value>
        <unit/>
      </serial>
      <concentration>
        <value>3.19730772727</value>
        <unit>mmol/g</unit>
      </concentration>
    </des>
    <des>
      <sample_temp>
        <value>20.248598</value>
        <unit>C</unit>
      </sample_temp>
      <index>18</index>
      <volume>
        <value>0.112486843</value>
        <unit>L</unit>
      </volume>
      <pressure>
        <value>8.96250481305</value>
        <unit>bar</unit>
      </pressure>
      <time>
        <value>36143.016</value>
        <unit>s (seconds)</unit>
      </time>
      <serial>
        <value>18.0</value>
        <unit/>
      </serial>
      <concentration>
        <value>3.17974772727</value>
        <unit>mmol/g</unit>
      </concentration>
    </des>
    <des>
      <sample_temp>
        <value>20.26298</value>
        <unit>C</unit>
      </sample_temp>
      <index>19</index>
      <volume>
        <value>0.110807306</value>
        <unit>L</unit>
      </volume>
      <pressure>
        <value>6.86838889452</value>
        <unit>bar</unit>
      </pressure>
      <time>
        <value>38196.994</value>
        <unit>s (seconds)</unit>
      </time>
      <serial>
        <value>19.0</value>
        <unit/>
      </serial>
      <concentration>
        <value>3.13227090909</value>
        <unit>mmol/g</unit>
      </concentration>
    </des>
    <des>
      <sample_temp>
        <value>20.23002</value>
        <unit>C</unit>
      </sample_temp>
      <index>20</index>
      <volume>
        <value>0.108017408</value>
        <unit>L</unit>
      </volume>
      <pressure>
        <value>4.98334177728</value>
        <unit>bar</unit>
      </pressure>
      <time>
        <value>40166.998</value>
        <unit>s (seconds)</unit>
      </time>
      <serial>
        <value>20.0</value>
        <unit/>
      </serial>
      <concentration>
        <value>3.05340681818</value>
        <unit>mmol/g</unit>
      </concentration>
    </des>
    <des>
      <sample_temp>
        <value>20.09158</value>
        <unit>C</unit>
      </sample_temp>
      <index>21</index>
      <volume>
        <value>0.102852636</value>
        <unit>L</unit>
      </volume>
      <pressure>
        <value>3.22146012767</value>
        <unit>bar</unit>
      </pressure>
      <time>
        <value>42169.0</value>
        <unit>s (seconds)</unit>
      </time>
      <serial>
        <value>21.0</value>
        <unit/>
      </serial>
      <concentration>
        <value>2.90741045455</value>
        <unit>mmol/g</unit>
      </concentration>
    </des>
    <des>
      <sample_temp>
        <value>19.915626</value>
        <unit>C</unit>
      </sample_temp>
      <index>22</index>
      <volume>
        <value>0.093976287</value>
        <unit>L</unit>
      </volume>
      <pressure>
        <value>1.8048312899</value>
        <unit>bar</unit>
      </pressure>
      <time>
        <value>44056.015</value>
        <unit>s (seconds)</unit>
      </time>
      <serial>
        <value>22.0</value>
        <unit/>
      </serial>
      <concentration>
        <value>2.65649636364</value>
        <unit>mmol/g</unit>
      </concentration>
    </des>
    <des>
      <sample_temp>
        <value>19.940622</value>
        <unit>C</unit>
      </sample_temp>
      <index>23</index>
      <volume>
        <value>0.089267054</value>
        <unit>L</unit>
      </volume>
      <pressure>
        <value>1.40234268923</value>
        <unit>bar</unit>
      </pressure>
      <time>
        <value>45942.005</value>
        <unit>s (seconds)</unit>
      </time>
      <serial>
        <value>23.0</value>
        <unit/>
      </serial>
      <concentration>
        <value>2.52337681818</value>
        <unit>mmol/g</unit>
      </concentration>
    </des>
    <des>
      <sample_temp>
        <value>20.176273</value>
        <unit>C</unit>
      </sample_temp>
      <index>24</index>
      <volume>
        <value>0.084561924</value>
        <unit>L</unit>
      </volume>
      <pressure>
        <value>1.11641605026</value>
        <unit>bar</unit>
      </pressure>
      <time>
        <value>47826.99</value>
        <unit>s (seconds)</unit>
      </time>
      <serial>
        <value>24.0</value>
        <unit/>
      </serial>
      <concentration>
        <value>2.39037363636</value>
        <unit>mmol/g</unit>
      </concentration>
    </des>
    <des>
      <sample_temp>
        <value>19.936281</value>
        <unit>C</unit>
      </sample_temp>
      <index>25</index>
      <volume>
        <value>0.080069441</value>
        <unit>L</unit>
      </volume>
      <pressure>
        <value>0.907053602189</value>
        <unit>bar</unit>
      </pressure>
      <time>
        <value>49711.998</value>
        <unit>s (seconds)</unit>
      </time>
      <serial>
        <value>25.0</value>
        <unit/>
      </serial>
      <concentration>
        <value>2.26338136364</value>
        <unit>mmol/g</unit>
      </concentration>
    </des>
    <ads>
      <sample_temp>
        <value>20.383717</value>
        <unit>C</unit>
      </sample_temp>
      <index>0</index>
      <volume>
        <value>-9e-09</value>
        <unit>L</unit>
      </volume>
      <pressure>
        <value>0.000300703110751</value>
        <unit>bar</unit>
      </pressure>
      <time>
        <value>1.011</value>
        <unit>s (seconds)</unit>
      </time>
      <serial>
        <value>0.0</value>
        <unit/>
      </serial>
      <concentration>
        <value>-2.27272727273e-07</value>
        <unit>mmol/g</unit>
      </concentration>
    </ads>
    <ads>
      <sample_temp>
        <value>20.045157</value>
        <unit>C</unit>
      </sample_temp>
      <index>1</index>
      <volume>
        <value>0.056767003</value>
        <unit>L</unit>
      </volume>
      <pressure>
        <value>0.483707366501</value>
        <unit>bar</unit>
      </pressure>
      <time>
        <value>2059.994</value>
        <unit>s (seconds)</unit>
      </time>
      <serial>
        <value>1.0</value>
        <unit/>
      </serial>
      <concentration>
        <value>1.60467431818</value>
        <unit>mmol/g</unit>
      </concentration>
    </ads>
    <ads>
      <sample_temp>
        <value>19.778561</value>
        <unit>C</unit>
      </sample_temp>
      <index>2</index>
      <volume>
        <value>0.084975229</value>
        <unit>L</unit>
      </volume>
      <pressure>
        <value>1.68151484446</value>
        <unit>bar</unit>
      </pressure>
      <time>
        <value>4041.017</value>
        <unit>s (seconds)</unit>
      </time>
      <serial>
        <value>2.0</value>
        <unit/>
      </serial>
      <concentration>
        <value>2.40205681818</value>
        <unit>mmol/g</unit>
      </concentration>
    </ads>
    <ads>
      <sample_temp>
        <value>20.046807</value>
        <unit>C</unit>
      </sample_temp>
      <index>3</index>
      <volume>
        <value>0.095727558</value>
        <unit>L</unit>
      </volume>
      <pressure>
        <value>3.33088560138</value>
        <unit>bar</unit>
      </pressure>
      <time>
        <value>6014.009</value>
        <unit>s (seconds)</unit>
      </time>
      <serial>
        <value>3.0</value>
        <unit/>
      </serial>
      <concentration>
        <value>2.70600068182</value>
        <unit>mmol/g</unit>
      </concentration>
    </ads>
    <ads>
      <sample_temp>
        <value>19.875179</value>
        <unit>C</unit>
      </sample_temp>
      <index>4</index>
      <volume>
        <value>0.100716989</value>
        <unit>L</unit>
      </volume>
      <pressure>
        <value>5.16102543317</value>
        <unit>bar</unit>
      </pressure>
      <time>
        <value>7999.996</value>
        <unit>s (seconds)</unit>
      </time>
      <serial>
        <value>4.0</value>
        <unit/>
      </serial>
      <concentration>
        <value>2.84704068182</value>
        <unit>mmol/g</unit>
      </concentration>
    </ads>
    <ads>
      <sample_temp>
        <value>19.931249</value>
        <unit>C</unit>
      </sample_temp>
      <index>5</index>
      <volume>
        <value>0.103299739</value>
        <unit>L</unit>
      </volume>
      <pressure>
        <value>6.99846083696</value>
        <unit>bar</unit>
      </pressure>
      <time>
        <value>9984.998</value>
        <unit>s (seconds)</unit>
      </time>
      <serial>
        <value>5.0</value>
        <unit/>
      </serial>
      <concentration>
        <value>2.92004909091</value>
        <unit>mmol/g</unit>
      </concentration>
    </ads>
    <ads>
      <sample_temp>
        <value>19.839249</value>
        <unit>C</unit>
      </sample_temp>
      <index>6</index>
      <volume>
        <value>0.104833281</value>
        <unit>L</unit>
      </volume>
      <pressure>
        <value>8.92211064951</value>
        <unit>bar</unit>
      </pressure>
      <time>
        <value>12040.994</value>
        <unit>s (seconds)</unit>
      </time>
      <serial>
        <value>6.0</value>
        <unit/>
      </serial>
      <concentration>
        <value>2.96339886364</value>
        <unit>mmol/g</unit>
      </concentration>
    </ads>
    <ads>
      <sample_temp>
        <value>19.954592</value>
        <unit>C</unit>
      </sample_temp>
      <index>7</index>
      <volume>
        <value>0.105632849</value>
        <unit>L</unit>
      </volume>
      <pressure>
        <value>10.7862397406</value>
        <unit>bar</unit>
      </pressure>
      <time>
        <value>14034.995</value>
        <unit>s (seconds)</unit>
      </time>
      <serial>
        <value>7.0</value>
        <unit/>
      </serial>
      <concentration>
        <value>2.98600090909</value>
        <unit>mmol/g</unit>
      </concentration>
    </ads>
    <ads>
      <sample_temp>
        <value>20.277274</value>
        <unit>C</unit>
      </sample_temp>
      <index>8</index>
      <volume>
        <value>0.106016591</value>
        <unit>L</unit>
      </volume>
      <pressure>
        <value>12.7836153612</value>
        <unit>bar</unit>
      </pressure>
      <time>
        <value>15945.013</value>
        <unit>s (seconds)</unit>
      </time>
      <serial>
        <value>8.0</value>
        <unit/>
      </serial>
      <concentration>
        <value>2.99684840909</value>
        <unit>mmol/g</unit>
      </concentration>
    </ads>
    <ads>
      <sample_temp>
        <value>20.144671</value>
        <unit>C</unit>
      </sample_temp>
      <index>9</index>
      <volume>
        <value>0.105944976</value>
        <unit>L</unit>
      </volume>
      <pressure>
        <value>14.7090485358</value>
        <unit>bar</unit>
      </pressure>
      <time>
        <value>17868.003</value>
        <unit>s (seconds)</unit>
      </time>
      <serial>
        <value>9.0</value>
        <unit/>
      </serial>
      <concentration>
        <value>2.99482386364</value>
        <unit>mmol/g</unit>
      </concentration>
    </ads>
    <ads>
      <sample_temp>
        <value>20.13456</value>
        <unit>C</unit>
      </sample_temp>
      <index>10</index>
      <volume>
        <value>0.105630651</value>
        <unit>L</unit>
      </volume>
      <pressure>
        <value>16.7555882055</value>
        <unit>bar</unit>
      </pressure>
      <time>
        <value>19838.0</value>
        <unit>s (seconds)</unit>
      </time>
      <serial>
        <value>10.0</value>
        <unit/>
      </serial>
      <concentration>
        <value>2.98593863636</value>
        <unit>mmol/g</unit>
      </concentration>
    </ads>
    <ads>
      <sample_temp>
        <value>19.696858</value>
        <unit>C</unit>
      </sample_temp>
      <index>11</index>
      <volume>
        <value>0.105028282</value>
        <unit>L</unit>
      </volume>
      <pressure>
        <value>18.6094842436</value>
        <unit>bar</unit>
      </pressure>
      <time>
        <value>21760.996</value>
        <unit>s (seconds)</unit>
      </time>
      <serial>
        <value>11.0</value>
        <unit/>
      </serial>
      <concentration>
        <value>2.96891113636</value>
        <unit>mmol/g</unit>
      </concentration>
    </ads>
    <ads>
      <sample_temp>
        <value>19.929434</value>
        <unit>C</unit>
      </sample_temp>
      <index>12</index>
      <volume>
        <value>0.104739859</value>
        <unit>L</unit>
      </volume>
      <pressure>
        <value>20.3595298409</value>
        <unit>bar</unit>
      </pressure>
      <time>
        <value>23684.983</value>
        <unit>s (seconds)</unit>
      </time>
      <serial>
        <value>12.0</value>
        <unit/>
      </serial>
      <concentration>
        <value>2.96075795455</value>
        <unit>mmol/g</unit>
      </concentration>
    </ads>
    <ads>
      <sample_temp>
        <value>20.124895</value>
        <unit>C</unit>
      </sample_temp>
      <index>13</index>
      <volume>
        <value>0.103832192</value>
        <unit>L</unit>
      </volume>
      <pressure>
        <value>22.4416354241</value>
        <unit>bar</unit>
      </pressure>
      <time>
        <value>25670.996</value>
        <unit>s (seconds)</unit>
      </time>
      <serial>
        <value>13.0</value>
        <unit/>
      </serial>
      <concentration>
        <value>2.93510022727</value>
        <unit>mmol/g</unit>
      </concentration>
    </ads>
    <ads>
      <sample_temp>
        <value>19.751289</value>
        <unit>C</unit>
      </sample_temp>
      <index>14</index>
      <volume>
        <value>0.103159595</value>
        <unit>L</unit>
      </volume>
      <pressure>
        <value>24.3558212585</value>
        <unit>bar</unit>
      </pressure>
      <time>
        <value>27594.998</value>
        <unit>s (seconds)</unit>
      </time>
      <serial>
        <value>14.0</value>
        <unit/>
      </serial>
      <concentration>
        <value>2.9160875</value>
        <unit>mmol/g</unit>
      </concentration>
    </ads>
    <ads>
      <sample_temp>
        <value>20.276069</value>
        <unit>C</unit>
      </sample_temp>
      <index>15</index>
      <volume>
        <value>0.102522245</value>
        <unit>L</unit>
      </volume>
      <pressure>
        <value>26.2501874557</value>
        <unit>bar</unit>
      </pressure>
      <time>
        <value>29571.004</value>
        <unit>s (seconds)</unit>
      </time>
      <serial>
        <value>15.0</value>
        <unit/>
      </serial>
      <concentration>
        <value>2.89807113636</value>
        <unit>mmol/g</unit>
      </concentration>
    </ads>
    <ads>
      <sample_temp>
        <value>19.868919</value>
        <unit>C</unit>
      </sample_temp>
      <index>16</index>
      <volume>
        <value>0.101582074</value>
        <unit>L</unit>
      </volume>
      <pressure>
        <value>28.1707569156</value>
        <unit>bar</unit>
      </pressure>
      <time>
        <value>31628.003</value>
        <unit>s (seconds)</unit>
      </time>
      <serial>
        <value>16.0</value>
        <unit/>
      </serial>
      <concentration>
        <value>2.87149454545</value>
        <unit>mmol/g</unit>
      </concentration>
    </ads>
    <ads>
      <sample_temp>
        <value>20.131609</value>
        <unit>C</unit>
      </sample_temp>
      <index>17</index>
      <volume>
        <value>0.101033202</value>
        <unit>L</unit>
      </volume>
      <pressure>
        <value>30.243732901</value>
        <unit>bar</unit>
      </pressure>
      <time>
        <value>33626.997</value>
        <unit>s (seconds)</unit>
      </time>
      <serial>
        <value>17.0</value>
        <unit/>
      </serial>
      <concentration>
        <value>2.85597931818</value>
        <unit>mmol/g</unit>
      </concentration>
    </ads>
    <ads>
      <sample_temp>
        <value>20.282689</value>
        <unit>C</unit>
      </sample_temp>
      <index>18</index>
      <volume>
        <value>0.100611224</value>
        <unit>L</unit>
      </volume>
      <pressure>
        <value>32.1649103253</value>
        <unit>bar</unit>
      </pressure>
      <time>
        <value>35620.0</value>
        <unit>s (seconds)</unit>
      </time>
      <serial>
        <value>18.0</value>
        <unit/>
      </serial>
      <concentration>
        <value>2.84405090909</value>
        <unit>mmol/g</unit>
      </concentration>
    </ads>
    <ads>
      <sample_temp>
        <value>20.133778</value>
        <unit>C</unit>
      </sample_temp>
      <index>19</index>
      <volume>
        <value>0.099883975</value>
        <unit>L</unit>
      </volume>
      <pressure>
        <value>33.8448373695</value>
        <unit>bar</unit>
      </pressure>
      <time>
        <value>37536.992</value>
        <unit>s (seconds)</unit>
      </time>
      <serial>
        <value>19.0</value>
        <unit/>
      </serial>
      <concentration>
        <value>2.82349318182</value>
        <unit>mmol/g</unit>
      </concentration>
    </ads>
    <ads>
      <sample_temp>
        <value>20.174193</value>
        <unit>C</unit>
      </sample_temp>
      <index>20</index>
      <volume>
        <value>0.099267806</value>
        <unit>L</unit>
      </volume>
      <pressure>
        <value>35.6797953187</value>
        <unit>bar</unit>
      </pressure>
      <time>
        <value>39592.991</value>
        <unit>s (seconds)</unit>
      </time>
      <serial>
        <value>20.0</value>
        <unit/>
      </serial>
      <concentration>
        <value>2.80607545455</value>
        <unit>mmol/g</unit>
      </concentration>
    </ads>
    <ads>
      <sample_temp>
        <value>19.785063</value>
        <unit>C</unit>
      </sample_temp>
      <index>21</index>
      <volume>
        <value>0.098088123</value>
        <unit>L</unit>
      </volume>
      <pressure>
        <value>37.6771709393</value>
        <unit>bar</unit>
      </pressure>
      <time>
        <value>41513.999</value>
        <unit>s (seconds)</unit>
      </time>
      <serial>
        <value>21.0</value>
        <unit/>
      </serial>
      <concentration>
        <value>2.77272840909</value>
        <unit>mmol/g</unit>
      </concentration>
    </ads>
    <ads>
      <sample_temp>
        <value>19.809831</value>
        <unit>C</unit>
      </sample_temp>
      <index>22</index>
      <volume>
        <value>0.097727646</value>
        <unit>L</unit>
      </volume>
      <pressure>
        <value>39.5320701186</value>
        <unit>bar</unit>
      </pressure>
      <time>
        <value>43499.007</value>
        <unit>s (seconds)</unit>
      </time>
      <serial>
        <value>22.0</value>
        <unit/>
      </serial>
      <concentration>
        <value>2.76253863636</value>
        <unit>mmol/g</unit>
      </concentration>
    </ads>
    <ads>
      <sample_temp>
        <value>20.286663</value>
        <unit>C</unit>
      </sample_temp>
      <index>23</index>
      <volume>
        <value>0.099172163</value>
        <unit>L</unit>
      </volume>
      <pressure>
        <value>41.7602796636</value>
        <unit>bar</unit>
      </pressure>
      <time>
        <value>45426.991</value>
        <unit>s (seconds)</unit>
      </time>
      <serial>
        <value>23.0</value>
        <unit/>
      </serial>
      <concentration>
        <value>2.80337181818</value>
        <unit>mmol/g</unit>
      </concentration>
    </ads>
    <ads>
      <sample_temp>
        <value>19.806549</value>
        <unit>C</unit>
      </sample_temp>
      <index>24</index>
      <volume>
        <value>0.09887671</value>
        <unit>L</unit>
      </volume>
      <pressure>
        <value>43.8978518594</value>
        <unit>bar</unit>
      </pressure>
      <time>
        <value>47354.994</value>
        <unit>s (seconds)</unit>
      </time>
      <serial>
        <value>24.0</value>
        <unit/>
      </serial>
      <concentration>
        <value>2.79502</value>
        <unit>mmol/g</unit>
      </concentration>
    </ads>
    <ads>
      <sample_temp>
        <value>20.023642</value>
        <unit>C</unit>
      </sample_temp>
      <index>25</index>
      <volume>
        <value>0.101258961</value>
        <unit>L</unit>
      </volume>
      <pressure>
        <value>45.7948323032</value>
        <unit>bar</unit>
      </pressure>
      <time>
        <value>49277.996</value>
        <unit>s (seconds)</unit>
      </time>
      <serial>
        <value>25.0</value>
        <unit/>
      </serial>
      <concentration>
        <value>2.86236090909</value>
        <unit>mmol/g</unit>
      </concentration>
    </ads>
  </content>
  <header>
    <notes/>
    <filename>20150624_8852_Aliq3_CO2_20C_45bar_435_AMC</filename>
    <sample>
      <name>8852 pressure up to 20C</name>
      <lot>8852_Aliq3_CO2 with 20C</lot>
    </sample>
    <experiment>
      <started>20150624</started>
      <id>435</id>
      <name>8852 CO2 Aliq3</name>
    </experiment>
    <operator/>
    <absorbate>CO2</absorbate>
  </header>
  <dataset>20150624_8852_Aliq3_CO2_20C_45bar_435_AMC.xlsx</dataset>
</amc>
